[
  {
    "id": 1,
    "image": "what-i've-done.jpg",
    "title": "What I've Done",
    "artist": "Linkin Park",
    "released": 2007,
    "album": "Minutes To Midnight",
    "audio": "/songs/what-i've-done.mp3",
    "lyrics": "what-i've-done.txt",
    "playlist": "Eng Pops",
    "favourite":"true"
  },
  {
    "id": 2,
    "image": "need-you-now.jpg",
    "title": "Need You Now",
    "artist": "Lady A",
    "released": 2010,
    "album": "Lady Antebellum",
    "audio": "/songs/need-you-now.mp3",
    "lyrics": "need-you-now.txt",
    "playlist": "Eng Pops"
  },
  {
    "id": 3,
    "image": "dancing-with-your-ghost.jpg",
    "title": "Dancing With Your Ghost",
    "artist": "Sasha Alex Sloan",
    "released": 2019,
    "album": "Self Portrait",
    "audio": "/songs/dancing-with-your-ghost.mp3",
    "lyrics": "dancing-with-your-ghost.txt",
    "playlist": "Eng Pops"
  },
  {
    "id": 4,
    "image": "always.jpg",
    "title": "Always",
    "artist": "Isak Danielson",
    "released": 2018,
    "album": "Yours",
    "audio": "/songs/always.mp3",
    "lyrics": "dancing-with-your-ghost.txt",
    "playlist": ""
  },
  {
    "id": 5,
    "image": "criminal.jpg",
    "title": "Criminal",
    "artist": "Britney Spears",
    "released": 2011,
    "album": "Femme Fatale",
    "audio": "/songs/criminal.mp3",
    "lyrics": "criminal.txt",
    "playlist": ""
  },
  {
    "id": 6,
    "image": "only-teardrops.jpg",
    "title": "Only Teardrops",
    "artist": "Emmelie De Forest",
    "released": 2013,
    "album": "Only Teardrops",
    "audio": "/songs/only-teardrops.mp3",
    "lyrics": "only-teardrops.txt",
    "playlist": ""
  }
]
